{
  "project_info": {
    "project_number": "1047972837602",
    "project_id": "smsjo-nat",
    "storage_bucket": "smsjo-nat.appspot.com"
  },
  "client": [
    {
      "client_info": {
        "mobilesdk_app_id": "1:1047972837602:android:3e90ca0f1f2f479f0786bb",
        "android_client_info": {
          "package_name": "com.developer.sms"
        }
      },
      "oauth_client": [
        {
          "client_id": "1047972837602-2arpgmvdthk45rl3b54pebo6cpkkoiba.apps.googleusercontent.com",
          "client_type": 3
        }
      ],
      "api_key": [
        {
          "current_key": "AIzaSyAfROMHCfJkcnstQUugP7lHJ49YV5QUFk0"
        }
      ],
      "services": {
        "appinvite_service": {
          "other_platform_oauth_client": [
            {
              "client_id": "1047972837602-2arpgmvdthk45rl3b54pebo6cpkkoiba.apps.googleusercontent.com",
              "client_type": 3
            }
          ]
        }
      }
    }
  ],
  "configuration_version": "1"
}